django_data_import_management/__init__.py
django_data_import_management/admin.py
django_data_import_management/apps.py
django_data_import_management/models.py
django_data_import_management/settings.py
django_data_import_management/locale/zh_Hans/LC_MESSAGES/django.mo
django_data_import_management/locale/zh_Hans/LC_MESSAGES/django.po
django_data_import_management/migrations/0001_initial.py
django_data_import_management/migrations/0002_auto_20201210_2115.py
django_data_import_management/migrations/0003_auto_20201210_2149.py
django_data_import_management/migrations/0004_auto_20201211_0937.py
django_data_import_management/migrations/0005_auto_20201211_1047.py
django_data_import_management/migrations/0006_alter_djangodataimportitem_import_success_and_more.py
django_data_import_management/migrations/0007_alter_djangodataimportcase_title.py
django_data_import_management/migrations/__init__.py
django_data_import_management/static/django_data_import_management/js/django_data_import_management.js
django_data_import_management-0.2.1.dist-info/LICENSE
django_data_import_management-0.2.1.dist-info/METADATA
django_data_import_management-0.2.1.dist-info/WHEEL
django_data_import_management-0.2.1.dist-info/top_level.txt
django_data_import_management-0.2.1.dist-info/RECORD
