Metadata-Version: 2.1
Name: django-data-import-management
Version: 0.2.1
Summary: Django data import management application.
Author: Qian DingFeng
Author-email: qiandingfeng@zencore.cn
Maintainer: Qian DingFeng
Maintainer-email: qiandingfeng@zencore.cn
License: MIT
Keywords: django extentions
Classifier: Development Status :: 5 - Production/Stable
Classifier: Intended Audience :: Developers
Classifier: Topic :: Software Development :: Libraries :: Python Modules
Classifier: License :: OSI Approved :: MIT License
Classifier: Programming Language :: Python :: 3
Classifier: Programming Language :: Python :: 3 :: Only
License-File: LICENSE
Requires-Dist: django
Requires-Dist: django-static-jquery-ui
Requires-Dist: django-static-fontawesome
Requires-Dist: django-safe-fields
Requires-Dist: django-changelist-toolbar-admin
Requires-Dist: django-object-toolbar-admin
Requires-Dist: zenutils
